{
  "transactions": [
    {
      "id": 1,
      "type": "expense",
      "amount": 15.5,
      "category": "餐饮",
      "note": "午餐",
      "date": "2025-01-01",
      "time": "12:30"
    },
    {
      "id": 2,
      "type": "income",
      "amount": 5000,
      "category": "工资",
      "note": "月薪",
      "date": "2025-01-05",
      "time": "10:00"
    },
    {
      "id": 3,
      "type": "expense",
      "amount": 50,
      "category": "交通",
      "note": "地铁卡充值",
      "date": "2025-01-10",
      "time": "08:15"
    }
  ],
  "balance": 4934.5,
  "next_id": 4
}

